xgbfir/__init__.py
xgbfir/main.py
xgbfir-0.3.1.dist-info/DESCRIPTION.rst
xgbfir-0.3.1.dist-info/METADATA
xgbfir-0.3.1.dist-info/RECORD
xgbfir-0.3.1.dist-info/WHEEL
xgbfir-0.3.1.dist-info/entry_points.txt
xgbfir-0.3.1.dist-info/metadata.json
xgbfir-0.3.1.dist-info/top_level.txt
