Metadata-Version: 1.1
Name: xgbfir
Version: 0.3.1
Summary: Xgbfir is a XGBoost model dump parser, which ranks features as well as feature interactions by different metrics
Home-page: https://github.com/limexp/xgbfir
Author: Boris Kostenko
Author-email: limexp@mail.ru
License: UNKNOWN
Download-URL: https://github.com/limexp/xgbfir/releases/tag/v0.3.1
Keywords: xgbfir,XGBoost,xgbfi,machine learning,ML
Platform: UNKNOWN
Classifier: Development Status :: 4 - Beta
Classifier: Environment :: Console
Classifier: Topic :: Scientific/Engineering :: Information Analysis
Classifier: Natural Language :: English
Classifier: Programming Language :: Python
Classifier: Programming Language :: Python :: 2.7
Classifier: Programming Language :: Python :: 3.5
Classifier: Programming Language :: Python :: 3.6
